odoo10_addon_account_mass_reconcile_by_purchase_line-10.0.1.0.0.99.dev2-py2.7-nspkg.pth
odoo/addons/account_mass_reconcile_by_purchase_line/README.rst
odoo/addons/account_mass_reconcile_by_purchase_line/__init__.py
odoo/addons/account_mass_reconcile_by_purchase_line/__manifest__.py
odoo/addons/account_mass_reconcile_by_purchase_line/i18n/account_mass_reconcile_by_purchase_line.pot
odoo/addons/account_mass_reconcile_by_purchase_line/models/__init__.py
odoo/addons/account_mass_reconcile_by_purchase_line/models/base_advanced_reconciliation.py
odoo/addons/account_mass_reconcile_by_purchase_line/models/mass_reconcile.py
odoo/addons/account_mass_reconcile_by_purchase_line/static/description/icon.png
odoo/addons/account_mass_reconcile_by_purchase_line/views/mass_reconcile.xml
odoo/addons/account_mass_reconcile_by_purchase_line/wizards/__init__.py
odoo/addons/account_mass_reconcile_by_purchase_line/wizards/advanced_reconciliation.py
odoo10_addon_account_mass_reconcile_by_purchase_line-10.0.1.0.0.99.dev2.dist-info/DESCRIPTION.rst
odoo10_addon_account_mass_reconcile_by_purchase_line-10.0.1.0.0.99.dev2.dist-info/METADATA
odoo10_addon_account_mass_reconcile_by_purchase_line-10.0.1.0.0.99.dev2.dist-info/RECORD
odoo10_addon_account_mass_reconcile_by_purchase_line-10.0.1.0.0.99.dev2.dist-info/WHEEL
odoo10_addon_account_mass_reconcile_by_purchase_line-10.0.1.0.0.99.dev2.dist-info/metadata.json
odoo10_addon_account_mass_reconcile_by_purchase_line-10.0.1.0.0.99.dev2.dist-info/namespace_packages.txt
odoo10_addon_account_mass_reconcile_by_purchase_line-10.0.1.0.0.99.dev2.dist-info/top_level.txt
