Metadata-Version: 2.0
Name: odoo10-addon-account-mass-reconcile-by-purchase-line
Version: 10.0.1.0.0.99.dev2
Summary: Allows to reconcile based on the PO line
Home-page: https://github.com/OCA/bank-statement-reconcile
Author: Eficent, Odoo Community Association (OCA)
Author-email: support@odoo-community.org
License: AGPL-3
Platform: UNKNOWN
Classifier: Programming Language :: Python
Classifier: Framework :: Odoo
Classifier: License :: OSI Approved :: GNU Affero General Public License v3
Requires-Python: ~=2.7
Requires-Dist: odoo (<10.1dev,>=10.0)
Requires-Dist: odoo10-addon-account-mass-reconcile
Requires-Dist: odoo10-addon-account-move-line-purchase-info
